er_person_generate/__init__.py
er_person_generate/altura.py
er_person_generate/cpf.py
er_person_generate/data_de_nascimento.py
er_person_generate/nome.py
er_person_generate/peso.py
er_person_generate/pessoa_F.py
er_person_generate/pessoa_M.py
er_person_generate/telefone.py
er_person_generate-1.5.0.dist-info/METADATA
er_person_generate-1.5.0.dist-info/WHEEL
er_person_generate-1.5.0.dist-info/top_level.txt
er_person_generate-1.5.0.dist-info/RECORD
