Metadata-Version: 2.1
Name: er_person_generate
Version: 1.5.0
Summary: Pacote de geração de dados de pessoas
Author: Erlanny
Author-email: erlannyrodrigues@gmail.com
Keywords: python,person,generate,brasil
Classifier: Development Status :: 3 - Alpha
Requires-Dist: numpy
Requires-Dist: faker
